tuilang/__init__.py
tuilang/__main__.py
tuilang/tuilang.py
tuilang-0.0.1.dist-info/LICENSE
tuilang-0.0.1.dist-info/METADATA
tuilang-0.0.1.dist-info/WHEEL
tuilang-0.0.1.dist-info/top_level.txt
tuilang-0.0.1.dist-info/RECORD
